scvae/__init__.py
scvae/__main__.py
scvae/__version__.py
scvae/cli.py
scvae/defaults.json
scvae/defaults.py
scvae/utilities.py
scvae/analyses/__init__.py
scvae/analyses/analyses.py
scvae/analyses/cross_analysis.py
scvae/analyses/images.py
scvae/analyses/prediction.py
scvae/analyses/subanalyses.py
scvae/analyses/decomposition/__init__.py
scvae/analyses/decomposition/decomposition.py
scvae/analyses/decomposition/incremental_pca.py
scvae/analyses/figures/__init__.py
scvae/analyses/figures/cross_model.py
scvae/analyses/figures/histograms.py
scvae/analyses/figures/learning_curves.py
scvae/analyses/figures/matrices.py
scvae/analyses/figures/saving.py
scvae/analyses/figures/scatter.py
scvae/analyses/figures/series.py
scvae/analyses/figures/style.py
scvae/analyses/figures/utilities.py
scvae/analyses/metrics/__init__.py
scvae/analyses/metrics/clustering.py
scvae/analyses/metrics/correlations.py
scvae/analyses/metrics/summary.py
scvae/data/__init__.py
scvae/data/data_set.py
scvae/data/data_sets.json
scvae/data/internal_io.py
scvae/data/loaders.py
scvae/data/loading.py
scvae/data/parsing.py
scvae/data/processing.py
scvae/data/sparse.py
scvae/data/utilities.py
scvae/distributions/__init__.py
scvae/distributions/categorised.py
scvae/distributions/exponentially_modified_normal.py
scvae/distributions/lomax.py
scvae/distributions/multivariate_normal.py
scvae/distributions/utilities.py
scvae/distributions/zero_inflated.py
scvae/models/__init__.py
scvae/models/gaussian_mixture_variational_autoencoder.py
scvae/models/utilities.py
scvae/models/variational_autoencoder.py
scvae-2.1.4.dist-info/LICENSE.txt
scvae-2.1.4.dist-info/METADATA
scvae-2.1.4.dist-info/WHEEL
scvae-2.1.4.dist-info/entry_points.txt
scvae-2.1.4.dist-info/top_level.txt
scvae-2.1.4.dist-info/RECORD
