Metadata-Version: 2.1
Name: scvae
Version: 2.1.4
Summary: Model single-cell transcript counts using deep learning.
Home-page: http://github.com/scvae/scvae
Author: Christopher Heje Grønbech, Maximillian Fornitz Vording
Author-email: christopher.groenbech@qlucore.com
License: Apache 2.0
Platform: UNKNOWN
Classifier: Programming Language :: Python :: 3
Classifier: License :: OSI Approved :: Apache Software License
Classifier: Operating System :: OS Independent
Requires-Python: >=3.6, <3.8
Requires-Dist: importlib-resources (>=1.0)
Requires-Dist: loompy (>=2.0)
Requires-Dist: numpy (>=1.16)
Requires-Dist: matplotlib (>=2.0)
Requires-Dist: pandas (>=0.24)
Requires-Dist: pillow (>=5.4)
Requires-Dist: scikit-learn (>=0.20)
Requires-Dist: scipy (>=1.2)
Requires-Dist: seaborn (>=0.9)
Requires-Dist: tables (>=3.5)
Requires-Dist: tensorflow (<2,>=1.15.2)
Requires-Dist: tensorflow-probability (==0.7)
Provides-Extra: docs
Requires-Dist: pygments (>=2.4) ; extra == 'docs'
Requires-Dist: sphinx (>=2.2) ; extra == 'docs'
